flask_autoinject/__init__.py
flask_autoinject/contexts.py
flask_autoinject-2.0.2.dist-info/LICENSE
flask_autoinject-2.0.2.dist-info/METADATA
flask_autoinject-2.0.2.dist-info/WHEEL
flask_autoinject-2.0.2.dist-info/top_level.txt
flask_autoinject-2.0.2.dist-info/RECORD
