Metadata-Version: 2.1
Name: flask-autoinject
Version: 2.0.2
Summary: Flask support for dependency injection with autoinject
Home-page: https://github.com/turnbullerin/flask_autoinject
Author: Erin Turnbull
Author-email: erin.a.turnbull@gmail.com
Project-URL: Bug Tracker, https://github.com/turnbullerin/flask_autoinject/issues
Classifier: Programming Language :: Python :: 3
Classifier: License :: OSI Approved :: MIT License
Classifier: Operating System :: OS Independent
Requires-Python: >=3.7
License-File: LICENSE
Requires-Dist: autoinject (>=1.2.1)
Requires-Dist: flask
